<annotation>
    <folder>train</folder>
    <filename>1405.jpg</filename>
    <path>/Users/chadd/Documents/Chadd/Work/DSO/Model_Re-training/TensorFlow/workspace/training/images/train/1405.jpg</path>
    <source>
        <database>Unknown</database>
    </source>
    <size>
        <width>256</width>
        <height>256</height>
        <depth>3</depth>
    </size>
    <segmented>0</segmented>
    <object>
        <name>ship</name>
        <pose>Unspecified</pose>
        <truncated>0</truncated>
        <difficult>0</difficult>
        <bndbox>
            <xmin>0.5992307662963867</xmin>
            <ymin>192.04701232910156</ymin>
            <xmax>29.9427490234375</xmax>
            <ymax>220.85227966308594</ymax>
        </bndbox>
    </object>    <object>
        <name>ship</name>
        <pose>Unspecified</pose>
        <truncated>0</truncated>
        <difficult>0</difficult>
        <bndbox>
            <xmin>128.17674255371094</xmin>
            <ymin>200.21920776367188</ymin>
            <xmax>154.0220489501953</xmax>
            <ymax>226.01040649414062</ymax>
        </bndbox>
    </object>    <object>
        <name>ship</name>
        <pose>Unspecified</pose>
        <truncated>0</truncated>
        <difficult>0</difficult>
        <bndbox>
            <xmin>165.8749542236328</xmin>
            <ymin>199.08718872070312</ymin>
            <xmax>204.00148010253906</xmax>
            <ymax>236.8258056640625</ymax>
        </bndbox>
    </object>    <object>
        <name>airplane</name>
        <pose>Unspecified</pose>
        <truncated>0</truncated>
        <difficult>0</difficult>
        <bndbox>
            <xmin>184.0810546875</xmin>
            <ymin>92.53475189208984</ymin>
            <xmax>221.79510498046875</xmax>
            <ymax>130.31565856933594</ymax>
        </bndbox>
    </object>    <object>
        <name>bird</name>
        <pose>Unspecified</pose>
        <truncated>0</truncated>
        <difficult>0</difficult>
        <bndbox>
            <xmin>164.1524658203125</xmin>
            <ymin>23.399948120117188</ymin>
            <xmax>199.36325073242188</xmax>
            <ymax>58.104103088378906</ymax>
        </bndbox>
    </object>    <object>
        <name>cat</name>
        <pose>Unspecified</pose>
        <truncated>0</truncated>
        <difficult>0</difficult>
        <bndbox>
            <xmin>200.5133819580078</xmin>
            <ymin>28.099132537841797</ymin>
            <xmax>231.82078552246094</xmax>
            <ymax>59.74216079711914</ymax>
        </bndbox>
    </object>    <object>
        <name>automobile</name>
        <pose>Unspecified</pose>
        <truncated>0</truncated>
        <difficult>0</difficult>
        <bndbox>
            <xmin>74.27151489257812</xmin>
            <ymin>212.1243896484375</ymin>
            <xmax>109.09654235839844</xmax>
            <ymax>246.98953247070312</ymax>
        </bndbox>
    </object>    <object>
        <name>deer</name>
        <pose>Unspecified</pose>
        <truncated>0</truncated>
        <difficult>0</difficult>
        <bndbox>
            <xmin>33.03093719482422</xmin>
            <ymin>168.65530395507812</ymin>
            <xmax>67.92925262451172</xmax>
            <ymax>203.89520263671875</ymax>
        </bndbox>
    </object>    <object>
        <name>dog</name>
        <pose>Unspecified</pose>
        <truncated>0</truncated>
        <difficult>0</difficult>
        <bndbox>
            <xmin>102.99720764160156</xmin>
            <ymin>164.10247802734375</ymin>
            <xmax>138.02415466308594</xmax>
            <ymax>198.84356689453125</ymax>
        </bndbox>
    </object>    <object>
        <name>cat</name>
        <pose>Unspecified</pose>
        <truncated>0</truncated>
        <difficult>0</difficult>
        <bndbox>
            <xmin>184.09776306152344</xmin>
            <ymin>136.26971435546875</ymin>
            <xmax>215.83457946777344</xmax>
            <ymax>168.00296020507812</ymax>
        </bndbox>
    </object>    <object>
        <name>automobile</name>
        <pose>Unspecified</pose>
        <truncated>0</truncated>
        <difficult>0</difficult>
        <bndbox>
            <xmin>123.61175537109375</xmin>
            <ymin>78.93228149414062</ymin>
            <xmax>157.98348999023438</xmax>
            <ymax>113.95783996582031</ymax>
        </bndbox>
    </object>    <object>
        <name>automobile</name>
        <pose>Unspecified</pose>
        <truncated>0</truncated>
        <difficult>0</difficult>
        <bndbox>
            <xmin>100.01925659179688</xmin>
            <ymin>77.2386703491211</ymin>
            <xmax>121.83708190917969</xmax>
            <ymax>99.1003646850586</ymax>
        </bndbox>
    </object>    <object>
        <name>cat</name>
        <pose>Unspecified</pose>
        <truncated>0</truncated>
        <difficult>0</difficult>
        <bndbox>
            <xmin>6.120708465576172</xmin>
            <ymin>94.9558334350586</ymin>
            <xmax>38.19279479980469</xmax>
            <ymax>126.92780303955078</ymax>
        </bndbox>
    </object>    <object>
        <name>bird</name>
        <pose>Unspecified</pose>
        <truncated>0</truncated>
        <difficult>0</difficult>
        <bndbox>
            <xmin>214.17733764648438</xmin>
            <ymin>216.04937744140625</ymin>
            <xmax>232.92056274414062</xmax>
            <ymax>234.79022216796875</ymax>
        </bndbox>
    </object>    <object>
        <name>airplane</name>
        <pose>Unspecified</pose>
        <truncated>0</truncated>
        <difficult>0</difficult>
        <bndbox>
            <xmin>174.12509155273438</xmin>
            <ymin>71.0783462524414</ymin>
            <xmax>189.98245239257812</xmax>
            <ymax>86.94493865966797</ymax>
        </bndbox>
    </object>    <object>
        <name>deer</name>
        <pose>Unspecified</pose>
        <truncated>0</truncated>
        <difficult>0</difficult>
        <bndbox>
            <xmin>61.19012451171875</xmin>
            <ymin>25.095457077026367</ymin>
            <xmax>79.86395263671875</xmax>
            <ymax>44.140045166015625</ymax>
        </bndbox>
    </object>    <object>
        <name>frog</name>
        <pose>Unspecified</pose>
        <truncated>0</truncated>
        <difficult>0</difficult>
        <bndbox>
            <xmin>26.29654884338379</xmin>
            <ymin>49.89191436767578</ymin>
            <xmax>51.76141357421875</xmax>
            <ymax>75.60530090332031</ymax>
        </bndbox>
    </object>
</annotation>
