<annotation>
    <folder>train</folder>
    <filename>254.jpg</filename>
    <path>/Users/chadd/Documents/Chadd/Work/DSO/Model_Re-training/TensorFlow/workspace/training/images/train/254.jpg</path>
    <source>
        <database>Unknown</database>
    </source>
    <size>
        <width>256</width>
        <height>256</height>
        <depth>3</depth>
    </size>
    <segmented>0</segmented>
    <object>
        <name>automobile</name>
        <pose>Unspecified</pose>
        <truncated>0</truncated>
        <difficult>0</difficult>
        <bndbox>
            <xmin>105.96182250976562</xmin>
            <ymin>53.913143157958984</ymin>
            <xmax>134.85964965820312</xmax>
            <ymax>82.79267120361328</ymax>
        </bndbox>
    </object>    <object>
        <name>ship</name>
        <pose>Unspecified</pose>
        <truncated>0</truncated>
        <difficult>0</difficult>
        <bndbox>
            <xmin>107.28013610839844</xmin>
            <ymin>119.18888092041016</ymin>
            <xmax>128.86183166503906</xmax>
            <ymax>141.09078979492188</ymax>
        </bndbox>
    </object>    <object>
        <name>ship</name>
        <pose>Unspecified</pose>
        <truncated>0</truncated>
        <difficult>0</difficult>
        <bndbox>
            <xmin>196.1144561767578</xmin>
            <ymin>9.220714569091797</ymin>
            <xmax>230.9210968017578</xmax>
            <ymax>44.04750442504883</ymax>
        </bndbox>
    </object>    <object>
        <name>ship</name>
        <pose>Unspecified</pose>
        <truncated>0</truncated>
        <difficult>0</difficult>
        <bndbox>
            <xmin>201.93910217285156</xmin>
            <ymin>149.35623168945312</ymin>
            <xmax>239.6373748779297</xmax>
            <ymax>187.87994384765625</ymax>
        </bndbox>
    </object>    <object>
        <name>airplane</name>
        <pose>Unspecified</pose>
        <truncated>0</truncated>
        <difficult>0</difficult>
        <bndbox>
            <xmin>33.99188232421875</xmin>
            <ymin>120.87974548339844</ymin>
            <xmax>66.11922454833984</xmax>
            <ymax>152.97105407714844</ymax>
        </bndbox>
    </object>    <object>
        <name>airplane</name>
        <pose>Unspecified</pose>
        <truncated>0</truncated>
        <difficult>0</difficult>
        <bndbox>
            <xmin>143.12217712402344</xmin>
            <ymin>69.13540649414062</ymin>
            <xmax>178.3776397705078</xmax>
            <ymax>103.66583251953125</ymax>
        </bndbox>
    </object>    <object>
        <name>frog</name>
        <pose>Unspecified</pose>
        <truncated>0</truncated>
        <difficult>0</difficult>
        <bndbox>
            <xmin>210.8748321533203</xmin>
            <ymin>107.06214904785156</ymin>
            <xmax>248.85081481933594</xmax>
            <ymax>145.28404235839844</ymax>
        </bndbox>
    </object>    <object>
        <name>bird</name>
        <pose>Unspecified</pose>
        <truncated>0</truncated>
        <difficult>0</difficult>
        <bndbox>
            <xmin>215.35702514648438</xmin>
            <ymin>61.30245590209961</ymin>
            <xmax>246.99734497070312</xmax>
            <ymax>93.00732421875</ymax>
        </bndbox>
    </object>    <object>
        <name>automobile</name>
        <pose>Unspecified</pose>
        <truncated>0</truncated>
        <difficult>0</difficult>
        <bndbox>
            <xmin>17.1357479095459</xmin>
            <ymin>209.2669677734375</ymin>
            <xmax>39.151145935058594</xmax>
            <ymax>231.02862548828125</ymax>
        </bndbox>
    </object>    <object>
        <name>cat</name>
        <pose>Unspecified</pose>
        <truncated>0</truncated>
        <difficult>0</difficult>
        <bndbox>
            <xmin>89.47991943359375</xmin>
            <ymin>198.1576690673828</ymin>
            <xmax>126.86325073242188</xmax>
            <ymax>236.29905700683594</ymax>
        </bndbox>
    </object>    <object>
        <name>cat</name>
        <pose>Unspecified</pose>
        <truncated>0</truncated>
        <difficult>0</difficult>
        <bndbox>
            <xmin>57.095069885253906</xmin>
            <ymin>163.05548095703125</ymin>
            <xmax>78.97376251220703</xmax>
            <ymax>184.778076171875</ymax>
        </bndbox>
    </object>    <object>
        <name>deer</name>
        <pose>Unspecified</pose>
        <truncated>0</truncated>
        <difficult>0</difficult>
        <bndbox>
            <xmin>27.260921478271484</xmin>
            <ymin>84.90730285644531</ymin>
            <xmax>52.90281295776367</xmax>
            <ymax>110.84487915039062</ymax>
        </bndbox>
    </object>    <object>
        <name>ship</name>
        <pose>Unspecified</pose>
        <truncated>0</truncated>
        <difficult>0</difficult>
        <bndbox>
            <xmin>18.28787612915039</xmin>
            <ymin>61.367149353027344</ymin>
            <xmax>39.79265594482422</xmax>
            <ymax>83.01314544677734</ymax>
        </bndbox>
    </object>    <object>
        <name>bird</name>
        <pose>Unspecified</pose>
        <truncated>0</truncated>
        <difficult>0</difficult>
        <bndbox>
            <xmin>160.1220703125</xmin>
            <ymin>116.00939178466797</ymin>
            <xmax>194.93569946289062</xmax>
            <ymax>150.6076202392578</ymax>
        </bndbox>
    </object>    <object>
        <name>dog</name>
        <pose>Unspecified</pose>
        <truncated>0</truncated>
        <difficult>0</difficult>
        <bndbox>
            <xmin>164.93460083007812</xmin>
            <ymin>215.6680908203125</ymin>
            <xmax>193.9818115234375</xmax>
            <ymax>244.80328369140625</ymax>
        </bndbox>
    </object>    <object>
        <name>dog</name>
        <pose>Unspecified</pose>
        <truncated>0</truncated>
        <difficult>0</difficult>
        <bndbox>
            <xmin>200.02659606933594</xmin>
            <ymin>190.73243713378906</ymin>
            <xmax>237.8376922607422</xmax>
            <ymax>227.88661193847656</ymax>
        </bndbox>
    </object>    <object>
        <name>ship</name>
        <pose>Unspecified</pose>
        <truncated>0</truncated>
        <difficult>0</difficult>
        <bndbox>
            <xmin>119.32203674316406</xmin>
            <ymin>168.14337158203125</ymin>
            <xmax>147.8785858154297</xmax>
            <ymax>196.85501098632812</ymax>
        </bndbox>
    </object>    <object>
        <name>airplane</name>
        <pose>Unspecified</pose>
        <truncated>0</truncated>
        <difficult>0</difficult>
        <bndbox>
            <xmin>119.32203674316406</xmin>
            <ymin>168.14337158203125</ymin>
            <xmax>147.8785858154297</xmax>
            <ymax>196.85501098632812</ymax>
        </bndbox>
    </object>    <object>
        <name>deer</name>
        <pose>Unspecified</pose>
        <truncated>0</truncated>
        <difficult>0</difficult>
        <bndbox>
            <xmin>152.3211212158203</xmin>
            <ymin>6.033056259155273</ymin>
            <xmax>173.92787170410156</xmax>
            <ymax>27.864133834838867</ymax>
        </bndbox>
    </object>
</annotation>
