<annotation>
    <folder>train</folder>
    <filename>431.jpg</filename>
    <path>/Users/chadd/Documents/Chadd/Work/DSO/Model_Re-training/TensorFlow/workspace/training/images/train/431.jpg</path>
    <source>
        <database>Unknown</database>
    </source>
    <size>
        <width>256</width>
        <height>256</height>
        <depth>3</depth>
    </size>
    <segmented>0</segmented>
    <object>
        <name>ship</name>
        <pose>Unspecified</pose>
        <truncated>0</truncated>
        <difficult>0</difficult>
        <bndbox>
            <xmin>22.010507583618164</xmin>
            <ymin>3.0713882446289062</ymin>
            <xmax>53.96900939941406</xmax>
            <ymax>34.844688415527344</ymax>
        </bndbox>
    </object>    <object>
        <name>ship</name>
        <pose>Unspecified</pose>
        <truncated>0</truncated>
        <difficult>0</difficult>
        <bndbox>
            <xmin>117.09916687011719</xmin>
            <ymin>123.98921966552734</ymin>
            <xmax>148.88743591308594</xmax>
            <ymax>155.5936737060547</ymax>
        </bndbox>
    </object>    <object>
        <name>bird</name>
        <pose>Unspecified</pose>
        <truncated>0</truncated>
        <difficult>0</difficult>
        <bndbox>
            <xmin>154.1060028076172</xmin>
            <ymin>68.99954223632812</ymin>
            <xmax>173.0166473388672</xmax>
            <ymax>87.804443359375</ymax>
        </bndbox>
    </object>    <object>
        <name>ship</name>
        <pose>Unspecified</pose>
        <truncated>0</truncated>
        <difficult>0</difficult>
        <bndbox>
            <xmin>32.12297439575195</xmin>
            <ymin>127.15767669677734</ymin>
            <xmax>48.0035285949707</xmax>
            <ymax>142.92893981933594</ymax>
        </bndbox>
    </object>    <object>
        <name>frog</name>
        <pose>Unspecified</pose>
        <truncated>0</truncated>
        <difficult>0</difficult>
        <bndbox>
            <xmin>69.0107421875</xmin>
            <ymin>5.014558792114258</ymin>
            <xmax>101.03298950195312</xmax>
            <ymax>36.88665008544922</ymax>
        </bndbox>
    </object>    <object>
        <name>airplane</name>
        <pose>Unspecified</pose>
        <truncated>0</truncated>
        <difficult>0</difficult>
        <bndbox>
            <xmin>131.05154418945312</xmin>
            <ymin>170.9506072998047</ymin>
            <xmax>168.87738037109375</xmax>
            <ymax>208.67784118652344</ymax>
        </bndbox>
    </object>    <object>
        <name>airplane</name>
        <pose>Unspecified</pose>
        <truncated>0</truncated>
        <difficult>0</difficult>
        <bndbox>
            <xmin>126.30358123779297</xmin>
            <ymin>3.0748844146728516</ymin>
            <xmax>163.7531280517578</xmax>
            <ymax>40.780189514160156</ymax>
        </bndbox>
    </object>    <object>
        <name>dog</name>
        <pose>Unspecified</pose>
        <truncated>0</truncated>
        <difficult>0</difficult>
        <bndbox>
            <xmin>175.16964721679688</xmin>
            <ymin>164.99728393554688</ymin>
            <xmax>212.92074584960938</xmax>
            <ymax>202.64443969726562</ymax>
        </bndbox>
    </object>    <object>
        <name>airplane</name>
        <pose>Unspecified</pose>
        <truncated>0</truncated>
        <difficult>0</difficult>
        <bndbox>
            <xmin>208.06211853027344</xmin>
            <ymin>212.81869506835938</ymin>
            <xmax>239.77976989746094</xmax>
            <ymax>244.61868286132812</ymax>
        </bndbox>
    </object>    <object>
        <name>airplane</name>
        <pose>Unspecified</pose>
        <truncated>0</truncated>
        <difficult>0</difficult>
        <bndbox>
            <xmin>155.08982849121094</xmin>
            <ymin>45.078651428222656</ymin>
            <xmax>174.0621795654297</xmax>
            <ymax>64.00531768798828</ymax>
        </bndbox>
    </object>    <object>
        <name>bird</name>
        <pose>Unspecified</pose>
        <truncated>0</truncated>
        <difficult>0</difficult>
        <bndbox>
            <xmin>193.09088134765625</xmin>
            <ymin>100.30148315429688</ymin>
            <xmax>212.14910888671875</xmax>
            <ymax>118.9808349609375</ymax>
        </bndbox>
    </object>    <object>
        <name>frog</name>
        <pose>Unspecified</pose>
        <truncated>0</truncated>
        <difficult>0</difficult>
        <bndbox>
            <xmin>94.04896545410156</xmin>
            <ymin>213.0804443359375</ymin>
            <xmax>112.63232421875</xmax>
            <ymax>232.07113647460938</ymax>
        </bndbox>
    </object>
</annotation>
