<annotation>
    <folder>train</folder>
    <filename>589.jpg</filename>
    <path>/Users/chadd/Documents/Chadd/Work/DSO/Model_Re-training/TensorFlow/workspace/training/images/train/589.jpg</path>
    <source>
        <database>Unknown</database>
    </source>
    <size>
        <width>256</width>
        <height>256</height>
        <depth>3</depth>
    </size>
    <segmented>0</segmented>
    <object>
        <name>frog</name>
        <pose>Unspecified</pose>
        <truncated>0</truncated>
        <difficult>0</difficult>
        <bndbox>
            <xmin>174.73924255371094</xmin>
            <ymin>170.98497009277344</ymin>
            <xmax>206.9954071044922</xmax>
            <ymax>203.15879821777344</ymax>
        </bndbox>
    </object>    <object>
        <name>frog</name>
        <pose>Unspecified</pose>
        <truncated>0</truncated>
        <difficult>0</difficult>
        <bndbox>
            <xmin>177.81405639648438</xmin>
            <ymin>53.075374603271484</ymin>
            <xmax>209.87298583984375</xmax>
            <ymax>84.97222900390625</ymax>
        </bndbox>
    </object>    <object>
        <name>dog</name>
        <pose>Unspecified</pose>
        <truncated>0</truncated>
        <difficult>0</difficult>
        <bndbox>
            <xmin>42.01203918457031</xmin>
            <ymin>29.289918899536133</ymin>
            <xmax>77.05119323730469</xmax>
            <ymax>64.1810073852539</ymax>
        </bndbox>
    </object>    <object>
        <name>airplane</name>
        <pose>Unspecified</pose>
        <truncated>0</truncated>
        <difficult>0</difficult>
        <bndbox>
            <xmin>129.35562133789062</xmin>
            <ymin>128.0195770263672</ymin>
            <xmax>150.999267578125</xmax>
            <ymax>149.82252502441406</ymax>
        </bndbox>
    </object>    <object>
        <name>dog</name>
        <pose>Unspecified</pose>
        <truncated>0</truncated>
        <difficult>0</difficult>
        <bndbox>
            <xmin>56.131595611572266</xmin>
            <ymin>208.97598266601562</ymin>
            <xmax>82.00238037109375</xmax>
            <ymax>234.8533935546875</ymax>
        </bndbox>
    </object>    <object>
        <name>bird</name>
        <pose>Unspecified</pose>
        <truncated>0</truncated>
        <difficult>0</difficult>
        <bndbox>
            <xmin>155.25949096679688</xmin>
            <ymin>1.2970151901245117</ymin>
            <xmax>176.89324951171875</xmax>
            <ymax>23.02435302734375</ymax>
        </bndbox>
    </object>    <object>
        <name>dog</name>
        <pose>Unspecified</pose>
        <truncated>0</truncated>
        <difficult>0</difficult>
        <bndbox>
            <xmin>145.92843627929688</xmin>
            <ymin>207.30020141601562</ymin>
            <xmax>180.64614868164062</xmax>
            <ymax>242.17572021484375</ymax>
        </bndbox>
    </object>    <object>
        <name>dog</name>
        <pose>Unspecified</pose>
        <truncated>0</truncated>
        <difficult>0</difficult>
        <bndbox>
            <xmin>122.22797393798828</xmin>
            <ymin>7.235637664794922</ymin>
            <xmax>141.1408233642578</xmax>
            <ymax>25.955734252929688</ymax>
        </bndbox>
    </object>    <object>
        <name>cat</name>
        <pose>Unspecified</pose>
        <truncated>0</truncated>
        <difficult>0</difficult>
        <bndbox>
            <xmin>96.1089859008789</xmin>
            <ymin>111.35116577148438</ymin>
            <xmax>127.77678680419922</xmax>
            <ymax>143.0076904296875</ymax>
        </bndbox>
    </object>    <object>
        <name>dog</name>
        <pose>Unspecified</pose>
        <truncated>0</truncated>
        <difficult>0</difficult>
        <bndbox>
            <xmin>186.04080200195312</xmin>
            <ymin>101.44111633300781</ymin>
            <xmax>223.9976806640625</xmax>
            <ymax>139.1953125</ymax>
        </bndbox>
    </object>    <object>
        <name>frog</name>
        <pose>Unspecified</pose>
        <truncated>0</truncated>
        <difficult>0</difficult>
        <bndbox>
            <xmin>115.13036346435547</xmin>
            <ymin>33.95071792602539</ymin>
            <xmax>143.63787841796875</xmax>
            <ymax>63.00130081176758</ymax>
        </bndbox>
    </object>    <object>
        <name>deer</name>
        <pose>Unspecified</pose>
        <truncated>0</truncated>
        <difficult>0</difficult>
        <bndbox>
            <xmin>102.94134521484375</xmin>
            <ymin>77.19432067871094</ymin>
            <xmax>122.08030700683594</xmax>
            <ymax>95.96101379394531</ymax>
        </bndbox>
    </object>    <object>
        <name>cat</name>
        <pose>Unspecified</pose>
        <truncated>0</truncated>
        <difficult>0</difficult>
        <bndbox>
            <xmin>145.17848205566406</xmin>
            <ymin>29.172374725341797</ymin>
            <xmax>163.94090270996094</xmax>
            <ymax>47.95846176147461</ymax>
        </bndbox>
    </object>    <object>
        <name>dog</name>
        <pose>Unspecified</pose>
        <truncated>0</truncated>
        <difficult>0</difficult>
        <bndbox>
            <xmin>131.23397827148438</xmin>
            <ymin>78.90153503417969</ymin>
            <xmax>165.9769287109375</xmax>
            <ymax>114.10990905761719</ymax>
        </bndbox>
    </object>    <object>
        <name>airplane</name>
        <pose>Unspecified</pose>
        <truncated>0</truncated>
        <difficult>0</difficult>
        <bndbox>
            <xmin>12.944135665893555</xmin>
            <ymin>70.09600830078125</ymin>
            <xmax>32.13810729980469</xmax>
            <ymax>88.97581481933594</ymax>
        </bndbox>
    </object>    <object>
        <name>cat</name>
        <pose>Unspecified</pose>
        <truncated>0</truncated>
        <difficult>0</difficult>
        <bndbox>
            <xmin>104.21260070800781</xmin>
            <ymin>178.0586395263672</ymin>
            <xmax>135.88455200195312</xmax>
            <ymax>209.76585388183594</ymax>
        </bndbox>
    </object>    <object>
        <name>dog</name>
        <pose>Unspecified</pose>
        <truncated>0</truncated>
        <difficult>0</difficult>
        <bndbox>
            <xmin>143.01812744140625</xmin>
            <ymin>174.20558166503906</ymin>
            <xmax>168.97244262695312</xmax>
            <ymax>200.0614471435547</ymax>
        </bndbox>
    </object>
</annotation>
