<annotation>
    <folder>train</folder>
    <filename>922.jpg</filename>
    <path>/Users/chadd/Documents/Chadd/Work/DSO/Model_Re-training/TensorFlow/workspace/training/images/train/922.jpg</path>
    <source>
        <database>Unknown</database>
    </source>
    <size>
        <width>256</width>
        <height>256</height>
        <depth>3</depth>
    </size>
    <segmented>0</segmented>
    <object>
        <name>ship</name>
        <pose>Unspecified</pose>
        <truncated>0</truncated>
        <difficult>0</difficult>
        <bndbox>
            <xmin>162.0487060546875</xmin>
            <ymin>148.19711303710938</ymin>
            <xmax>183.97344970703125</xmax>
            <ymax>170.00390625</ymax>
        </bndbox>
    </object>    <object>
        <name>bird</name>
        <pose>Unspecified</pose>
        <truncated>0</truncated>
        <difficult>0</difficult>
        <bndbox>
            <xmin>81.20030975341797</xmin>
            <ymin>158.34642028808594</ymin>
            <xmax>112.6584701538086</xmax>
            <ymax>189.8376007080078</ymax>
        </bndbox>
    </object>    <object>
        <name>cat</name>
        <pose>Unspecified</pose>
        <truncated>0</truncated>
        <difficult>0</difficult>
        <bndbox>
            <xmin>132.13296508789062</xmin>
            <ymin>55.111244201660156</ymin>
            <xmax>169.92147827148438</xmax>
            <ymax>92.67530059814453</ymax>
        </bndbox>
    </object>    <object>
        <name>airplane</name>
        <pose>Unspecified</pose>
        <truncated>0</truncated>
        <difficult>0</difficult>
        <bndbox>
            <xmin>179.96080017089844</xmin>
            <ymin>93.8756332397461</ymin>
            <xmax>195.91270446777344</xmax>
            <ymax>109.9092788696289</ymax>
        </bndbox>
    </object>    <object>
        <name>bird</name>
        <pose>Unspecified</pose>
        <truncated>0</truncated>
        <difficult>0</difficult>
        <bndbox>
            <xmin>197.124755859375</xmin>
            <ymin>119.02116394042969</ymin>
            <xmax>234.98104858398438</xmax>
            <ymax>156.6020965576172</ymax>
        </bndbox>
    </object>    <object>
        <name>dog</name>
        <pose>Unspecified</pose>
        <truncated>0</truncated>
        <difficult>0</difficult>
        <bndbox>
            <xmin>48.89796447753906</xmin>
            <ymin>1.4703025817871094</ymin>
            <xmax>87.18594360351562</xmax>
            <ymax>39.120845794677734</ymax>
        </bndbox>
    </object>    <object>
        <name>cat</name>
        <pose>Unspecified</pose>
        <truncated>0</truncated>
        <difficult>0</difficult>
        <bndbox>
            <xmin>99.943359375</xmin>
            <ymin>64.0592041015625</ymin>
            <xmax>116.00051879882812</xmax>
            <ymax>80.06492614746094</ymax>
        </bndbox>
    </object>    <object>
        <name>dog</name>
        <pose>Unspecified</pose>
        <truncated>0</truncated>
        <difficult>0</difficult>
        <bndbox>
            <xmin>215.04769897460938</xmin>
            <ymin>207.30422973632812</ymin>
            <xmax>249.99423217773438</xmax>
            <ymax>242.09857177734375</ymax>
        </bndbox>
    </object>    <object>
        <name>airplane</name>
        <pose>Unspecified</pose>
        <truncated>0</truncated>
        <difficult>0</difficult>
        <bndbox>
            <xmin>89.37874603271484</xmin>
            <ymin>208.12319946289062</ymin>
            <xmax>124.07015228271484</xmax>
            <ymax>243.11734008789062</ymax>
        </bndbox>
    </object>    <object>
        <name>airplane</name>
        <pose>Unspecified</pose>
        <truncated>0</truncated>
        <difficult>0</difficult>
        <bndbox>
            <xmin>152.00531005859375</xmin>
            <ymin>4.213300704956055</ymin>
            <xmax>187.09506225585938</xmax>
            <ymax>39.004615783691406</ymax>
        </bndbox>
    </object>    <object>
        <name>deer</name>
        <pose>Unspecified</pose>
        <truncated>0</truncated>
        <difficult>0</difficult>
        <bndbox>
            <xmin>3.1844491958618164</xmin>
            <ymin>141.0659942626953</ymin>
            <xmax>22.03650665283203</xmax>
            <ymax>160.0618133544922</ymax>
        </bndbox>
    </object>    <object>
        <name>bird</name>
        <pose>Unspecified</pose>
        <truncated>0</truncated>
        <difficult>0</difficult>
        <bndbox>
            <xmin>59.474082946777344</xmin>
            <ymin>52.131187438964844</ymin>
            <xmax>93.9643783569336</xmax>
            <ymax>87.0879135131836</ymax>
        </bndbox>
    </object>    <object>
        <name>bird</name>
        <pose>Unspecified</pose>
        <truncated>0</truncated>
        <difficult>0</difficult>
        <bndbox>
            <xmin>50.0882682800293</xmin>
            <ymin>210.8334197998047</ymin>
            <xmax>88.04499816894531</xmax>
            <ymax>248.6571807861328</ymax>
        </bndbox>
    </object>    <object>
        <name>bird</name>
        <pose>Unspecified</pose>
        <truncated>0</truncated>
        <difficult>0</difficult>
        <bndbox>
            <xmin>19.40892791748047</xmin>
            <ymin>59.99342727661133</ymin>
            <xmax>54.19927215576172</xmax>
            <ymax>94.87620544433594</ymax>
        </bndbox>
    </object>    <object>
        <name>frog</name>
        <pose>Unspecified</pose>
        <truncated>0</truncated>
        <difficult>0</difficult>
        <bndbox>
            <xmin>117.90383911132812</xmin>
            <ymin>115.90109252929688</ymin>
            <xmax>147.0927734375</xmax>
            <ymax>144.93728637695312</ymax>
        </bndbox>
    </object>
</annotation>
