<annotation>
    <folder>train</folder>
    <filename>941.jpg</filename>
    <path>/Users/chadd/Documents/Chadd/Work/DSO/Model_Re-training/TensorFlow/workspace/training/images/train/941.jpg</path>
    <source>
        <database>Unknown</database>
    </source>
    <size>
        <width>256</width>
        <height>256</height>
        <depth>3</depth>
    </size>
    <segmented>0</segmented>
    <object>
        <name>ship</name>
        <pose>Unspecified</pose>
        <truncated>0</truncated>
        <difficult>0</difficult>
        <bndbox>
            <xmin>48.975868225097656</xmin>
            <ymin>59.06378173828125</ymin>
            <xmax>86.63382720947266</xmax>
            <ymax>97.05455017089844</ymax>
        </bndbox>
    </object>    <object>
        <name>ship</name>
        <pose>Unspecified</pose>
        <truncated>0</truncated>
        <difficult>0</difficult>
        <bndbox>
            <xmin>4.390254020690918</xmin>
            <ymin>6.111004829406738</ymin>
            <xmax>26.065731048583984</xmax>
            <ymax>27.78936004638672</ymax>
        </bndbox>
    </object>    <object>
        <name>airplane</name>
        <pose>Unspecified</pose>
        <truncated>0</truncated>
        <difficult>0</difficult>
        <bndbox>
            <xmin>153.12962341308594</xmin>
            <ymin>184.8917694091797</ymin>
            <xmax>182.04917907714844</xmax>
            <ymax>213.92796325683594</ymax>
        </bndbox>
    </object>    <object>
        <name>ship</name>
        <pose>Unspecified</pose>
        <truncated>0</truncated>
        <difficult>0</difficult>
        <bndbox>
            <xmin>159.06703186035156</xmin>
            <ymin>72.02447509765625</ymin>
            <xmax>191.03025817871094</xmax>
            <ymax>104.14460754394531</ymax>
        </bndbox>
    </object>    <object>
        <name>airplane</name>
        <pose>Unspecified</pose>
        <truncated>0</truncated>
        <difficult>0</difficult>
        <bndbox>
            <xmin>59.152069091796875</xmin>
            <ymin>192.050048828125</ymin>
            <xmax>91.17910766601562</xmax>
            <ymax>223.83160400390625</ymax>
        </bndbox>
    </object>    <object>
        <name>automobile</name>
        <pose>Unspecified</pose>
        <truncated>0</truncated>
        <difficult>0</difficult>
        <bndbox>
            <xmin>78.01451873779297</xmin>
            <ymin>140.052001953125</ymin>
            <xmax>93.94139862060547</xmax>
            <ymax>155.91455078125</ymax>
        </bndbox>
    </object>    <object>
        <name>bird</name>
        <pose>Unspecified</pose>
        <truncated>0</truncated>
        <difficult>0</difficult>
        <bndbox>
            <xmin>26.965576171875</xmin>
            <ymin>99.12788391113281</ymin>
            <xmax>53.14338684082031</xmax>
            <ymax>124.86671447753906</ymax>
        </bndbox>
    </object>    <object>
        <name>deer</name>
        <pose>Unspecified</pose>
        <truncated>0</truncated>
        <difficult>0</difficult>
        <bndbox>
            <xmin>104.25846099853516</xmin>
            <ymin>200.2050323486328</ymin>
            <xmax>139.10057067871094</xmax>
            <ymax>234.74351501464844</ymax>
        </bndbox>
    </object>    <object>
        <name>ship</name>
        <pose>Unspecified</pose>
        <truncated>0</truncated>
        <difficult>0</difficult>
        <bndbox>
            <xmin>152.00662231445312</xmin>
            <ymin>109.24286651611328</ymin>
            <xmax>174.03701782226562</xmax>
            <ymax>131.0841827392578</ymax>
        </bndbox>
    </object>    <object>
        <name>ship</name>
        <pose>Unspecified</pose>
        <truncated>0</truncated>
        <difficult>0</difficult>
        <bndbox>
            <xmin>92.34993743896484</xmin>
            <ymin>54.126243591308594</ymin>
            <xmax>117.84615325927734</xmax>
            <ymax>79.99007415771484</ymax>
        </bndbox>
    </object>    <object>
        <name>deer</name>
        <pose>Unspecified</pose>
        <truncated>0</truncated>
        <difficult>0</difficult>
        <bndbox>
            <xmin>212.3791046142578</xmin>
            <ymin>134.09463500976562</ymin>
            <xmax>234.0066680908203</xmax>
            <ymax>155.95913696289062</ymax>
        </bndbox>
    </object>    <object>
        <name>dog</name>
        <pose>Unspecified</pose>
        <truncated>0</truncated>
        <difficult>0</difficult>
        <bndbox>
            <xmin>120.19888305664062</xmin>
            <ymin>15.133902549743652</ymin>
            <xmax>146.26156616210938</xmax>
            <ymax>41.01294708251953</ymax>
        </bndbox>
    </object>    <object>
        <name>airplane</name>
        <pose>Unspecified</pose>
        <truncated>0</truncated>
        <difficult>0</difficult>
        <bndbox>
            <xmin>162.26397705078125</xmin>
            <ymin>24.041122436523438</ymin>
            <xmax>183.94503784179688</xmax>
            <ymax>45.82623291015625</ymax>
        </bndbox>
    </object>    <object>
        <name>airplane</name>
        <pose>Unspecified</pose>
        <truncated>0</truncated>
        <difficult>0</difficult>
        <bndbox>
            <xmin>155.12782287597656</xmin>
            <ymin>148.11093139648438</ymin>
            <xmax>173.93202209472656</xmax>
            <ymax>166.96697998046875</ymax>
        </bndbox>
    </object>
</annotation>
